[{"Title":"Jazzheart... forever...","Description":"-","Genre":"Jazz","Country":"Korea, South","Language":"Korean","Source":{"Source1":"http://jazzheart.inlive.co.kr/listen.pls","Source2":"http://jazzheart.saycast.com/listen.pls","Source3":"-","Source4":"-","Source5":"-","Source6":"-"}},{"Title":"CBS 기독교방송 음악FM(부산)","Description":"-","Genre":"Christian","Country":"Korea, South","Language":"Korean","Source":{"Source1":"mms://media.biointernet.com/fm1021","Source2":"-","Source3":"-","Source4":"-","Source5":"-","Source6":"-"}},{"Title":"FEBC 극동방송(AM)","Description":"-","Genre":"Christian","Country":"Korea, South","Language":"Korean","Source":{"Source1":"mms://live.febc.net/LiveAm","Source2":"-","Source3":"-","Source4":"-","Source5":"-","Source6":"-"}},{"Title":"AFN Casey(동두천)","Description":"-","Genre":"Variety","Country":"Korea, South","Language":"English","Source":{"Source1":"http://provisioning.streamtheworld.com/pls/AFNP_CSYAAC.pls","Source2":"http://provisioning.streamtheworld.com/pls/AFNP_CSY.pls","Source3":"-","Source4":"-","Source5":"-","Source6":"-"}},{"Title":"AFN Kunsan","Description":"-","Genre":"Variety","Country":"Korea, South","Language":"English","Source":{"Source1":"http://provisioning.streamtheworld.com/pls/AFNP_KSNAAC.pls","Source2":"http://provisioning.streamtheworld.com/pls/AFNP_KSN.pls","Source3":"-","Source4":"-","Source5":"-","Source6":"-"}},{"Title":"AFN Osan","Description":"-","Genre":"Variety","Country":"Korea, South","Language":"English","Source":{"Source1":"http://provisioning.streamtheworld.com/pls/AFNP_OSNAAC.pls","Source2":"http://provisioning.streamtheworld.com/pls/AFNP_OSN.pls","Source3":"-","Source4":"-","Source5":"-","Source6":"-"}},{"Title":"AFN Yongsan","Description":"-","Genre":"Variety","Country":"Korea, South","Language":"English","Source":{"Source1":"http://provisioning.streamtheworld.com/pls/AFNP_YSNAAC.pls","Source2":"http://provisioning.streamtheworld.com/pls/AFNP_YSN.pls","Source3":"-","Source4":"-","Source5":"-","Source6":"-"}},{"Title":"AFN Daegu","Description":"-","Genre":"Variety","Country":"Korea, South","Language":"English","Source":{"Source1":"http://provisioning.streamtheworld.com/pls/AFNP_DGUAAC.pls","Source2":"http://provisioning.streamtheworld.com/pls/AFNP_DGU.pls","Source3":"-","Source4":"-","Source5":"-","Source6":"-"}},{"Title":"OMGKpop Radio","Description":"Seoul, Korea . Where Korean Pop Culture and Radio happen! Come join the fun today Join our Japanese Pop Culture fanpage facebook.com/omgjpop","Genre":"Pop","Country":"Korea, South","Language":"Japanese","Source":{"Source1":"http://stream.omgkpop.com:8234/stream","Source2":"-","Source3":"-","Source4":"-","Source5":"-","Source6":"-"}},{"Title":"KBS World Radio - German Stream","Description":"Shortwave program in German","Genre":"Variety","Country":"Korea, South","Language":"German","Source":{"Source1":"http://live.world.kbs.gscdn.com/cocotv/_definst_/CH00005/playlist.m3u8","Source2":"-","Source3":"-","Source4":"-","Source5":"-","Source6":"-"}},{"Title":"KBS World Radio - Channel 1","Description":"First channel of Korea's foreign language promotional broadcast","Genre":"Talk","Country":"Korea, South","Language":"-","Source":{"Source1":"http://kbsrki.gscdn.com/kbsrki1/_definst_/kbsrki1.stream/playlist.m3u8","Source2":"-","Source3":"-","Source4":"-","Source5":"-","Source6":"-"}},{"Title":"KBS World Radio - Channel 2","Description":"Second channel of Korea's foreign language promotional broadcast","Genre":"Talk","Country":"Korea, South","Language":"-","Source":{"Source1":"http://kbsrki.gscdn.com/kbsrki2/_definst_/kbsrki2.stream/playlist.m3u8","Source2":"-","Source3":"-","Source4":"-","Source5":"-","Source6":"-"}},{"Title":"KBS World Radio - Channel 3","Description":"Music channel of Korea's foreign language promotional broadcast. K-Pop Connection 24hr On-Air","Genre":"Pop","Country":"Korea, South","Language":"English","Source":{"Source1":"http://kbsrki.gscdn.com/kbsrki3/_definst_/kbsrki3.stream/playlist.m3u8","Source2":"-","Source3":"-","Source4":"-","Source5":"-","Source6":"-"}},{"Title":"Republic of Korea Top Radio","Description":"Korean Pop","Genre":"Rock-Pop","Country":"Korea, South","Language":"Korean","Source":{"Source1":"http://sc06.saycast.com:8026","Source2":"-","Source3":"-","Source4":"-","Source5":"-","Source6":"-"}},{"Title":"Love Galaxies","Description":"Classical Music 24 hours a day","Genre":"Classical","Country":"Korea, South","Language":"Korean","Source":{"Source1":"http://LOVEGALAXIES.inlive.co.kr/listen.pls","Source2":"-","Source3":"-","Source4":"-","Source5":"-","Source6":"-"}},{"Title":"KMStudio Classical Radio","Description":"Classical, New Age, Ambient, Chillout, Easy Listening, Instrumental","Genre":"Classical","Country":"Korea, South","Language":"Korean","Source":{"Source1":"http://AM98.5Mhz.net/listen.asx","Source2":"mms://AM98.5Mhz.net","Source3":"-","Source4":"-","Source5":"-","Source6":"-"}},{"Title":"Happyday New Age -  EZ Channel","Description":"Ambient, Electronica, Chillout and Ethnic","Genre":"New Age","Country":"Korea, South","Language":"English","Source":{"Source1":"http://inewage.com/listen.pls","Source2":"http://inewage.com/listen.ram","Source3":"-","Source4":"-","Source5":"-","Source6":"-"}},{"Title":"Happyday New Age - ELEC Channel","Description":"-","Genre":"Electronica-Ambient","Country":"Korea, South","Language":"English","Source":{"Source1":"http://inewage.com/listen.m3u","Source2":"-","Source3":"-","Source4":"-","Source5":"-","Source6":"-"}},{"Title":"Cast.cc","Description":"공지사항   2009-07-14 : [ccj^유니나] 하루를 즐겁게 하는 방법  방송듣기 http://cast.cc:8888  긍정적이고 낙관적인 사람과 교제하라 가까이 지내는 사람의 기분과 행동은 우리의 기분과 행동에 전염성이 있다.  자신감을 가져라 자신의 약점보다 장점을 바라보고 자기 비판보다 자신의 성공과 행복을 스스로에게 확신시킬 수 있는 사람만 성공한다.  남과 비교하지 말라 세상엔 당신보다 잘난 사람도 있고 못난 사람도 있게 마련이다.  행복해지겠다고 결심하라 사람은 자신이 작정한만큼 행복해질 수 있다. 자신의 태도가 주위 여건보다 훨씬 중요하다.  모든일에 머리를 쓰라 성공한 사람들은 항상 작은 일에도  머리를 써서 향상시킬 방법을 찾는다.  당신을 구속하는 것은 바로 당신의 생각이다. 인식전환을 통하여 행동의 변화와 운명의 변화를 꾀하자.","Genre":"Pop","Country":"Korea, South","Language":"Korean","Source":{"Source1":"http://cast.cc:8888/;","Source2":"-","Source3":"-","Source4":"-","Source5":"-","Source6":"-"}},{"Title":"DreamCast","Description":"-","Genre":"Pop","Country":"Korea, South","Language":"Korean","Source":{"Source1":"http://dream.saycast.com","Source2":"-","Source3":"-","Source4":"-","Source5":"-","Source6":"-"}},{"Title":"Far East Broadcasting Center (FEBC)  극동방송 (FM)","Description":"http://www.febc.net/intro This is Far East Broadcasting Center in Korea.","Genre":"Christian","Country":"Korea, South","Language":"Korean","Source":{"Source1":"http://mlive2.febc.net:1935/live/seoulfm/playlist.m3u8","Source2":"-","Source3":"-","Source4":"-","Source5":"-","Source6":"-"}},{"Title":"Gugak FM 99.1","Description":"Korean music","Genre":"Asian","Country":"Korea, South","Language":"Korean","Source":{"Source1":"http://mgugaklive.nowcdn.co.kr/gugakvideo/gugakvideo.stream/playlist.m3u8","Source2":"-","Source3":"-","Source4":"-","Source5":"-","Source6":"-"}},{"Title":"원주MBC 표준FM","Description":"-","Genre":"Variety","Country":"Korea, South","Language":"Korean","Source":{"Source1":"mms://live.wjmbc.co.kr/fm2","Source2":"-","Source3":"-","Source4":"-","Source5":"-","Source6":"-"}},{"Title":"CBS 기독교방송 표준FM(부산)","Description":"-","Genre":"Christian","Country":"Korea, South","Language":"Korean","Source":{"Source1":"http://media.biointernet.com/fm1029","Source2":"mms://media.biointernet.com/fm1029","Source3":"-","Source4":"-","Source5":"-","Source6":"-"}},{"Title":"Wonju MBC AM","Description":"-","Genre":"Public Radio","Country":"Korea, South","Language":"Korean","Source":{"Source1":"mms://live.wjmbc.co.kr/fm2","Source2":"-","Source3":"-","Source4":"-","Source5":"-","Source6":"-"}},{"Title":"Wonju MBC FM","Description":"-","Genre":"Public Radio","Country":"Korea, South","Language":"Korean","Source":{"Source1":"mms://live.wjmbc.co.kr/fm989","Source2":"-","Source3":"-","Source4":"-","Source5":"-","Source6":"-"}},{"Title":"Radio Kiss 인디뮤직 스페셜","Description":"Radio Kiss Indie music special","Genre":"Independent","Country":"Korea, South","Language":"Korean","Source":{"Source1":"mms://124.53.158.172:1156/;","Source2":"-","Source3":"-","Source4":"-","Source5":"-","Source6":"-"}},{"Title":"WOWCCM - 와우씨씨엠","Description":"https://www.facebook.com/wowccm/ Christian Music channel 136-853 Christian Broadcasting Station on the M-level 746 Jungrung 3-dong, Seongbuk-gu, Seoul","Genre":"Christian","Country":"Korea, South","Language":"Korean","Source":{"Source1":"http://wowccm.net/listen.pls","Source2":"http://sc11.saycast.com:8274/;","Source3":"-","Source4":"-","Source5":"-","Source6":"-"}}]